flightdata/__init__.py
flightdata/bindata.py
flightdata/coefficients.py
flightdata/flow.py
flightdata/origin.py
flightdata/py.typed
flightdata/state_maker.py
flightdata/base/__init__.py
flightdata/base/collection.py
flightdata/base/numpy_encoder.py
flightdata/base/table/__init__.py
flightdata/base/table/constructs.py
flightdata/base/table/label.py
flightdata/base/table/labelgroup.py
flightdata/base/table/labelgroups.py
flightdata/base/table/slicer.py
flightdata/base/table/table.py
flightdata/environment/__init__.py
flightdata/environment/environment.py
flightdata/environment/wind.py
flightdata/flight/__init__.py
flightdata/flight/ardupilot.py
flightdata/flight/fields.py
flightdata/flight/flight.py
flightdata/flight/parameters.py
flightdata/model/__init__.py
flightdata/model/aerodynamic.py
flightdata/model/thrust.py
flightdata/scripts/collect_logs.py
flightdata/scripts/flightline.py
flightdata/state/__init__.py
flightdata/state/alignment.py
flightdata/state/kinematics.py
flightdata/state/state.py
flightdata-0.3.4.dist-info/METADATA
flightdata-0.3.4.dist-info/WHEEL
flightdata-0.3.4.dist-info/entry_points.txt
flightdata-0.3.4.dist-info/licenses/LICENSE
flightdata-0.3.4.dist-info/RECORD
