Metadata-Version: 2.4
Name: flightdata
Version: 0.3.4
Summary: Python tools for handling flight data
Author-email: Thomas David <thomasdavid0@gmail.com>
License-File: LICENSE
Requires-Python: >=3.12
Requires-Dist: numpy>=2.1.3
Requires-Dist: pandas>=2.2.3
Requires-Dist: pfc-geometry>=0.2.19
Requires-Dist: pfcschemas>=0.1.12
Requires-Dist: simplejson>=3.20.1
Provides-Extra: dataflash
Requires-Dist: ardupilot-log-reader; extra == 'dataflash'
